imessageToolHp.py
imessageToolHp_package-0.1.dist-info/METADATA
imessageToolHp_package-0.1.dist-info/WHEEL
imessageToolHp_package-0.1.dist-info/top_level.txt
imessageToolHp_package-0.1.dist-info/RECORD
