Metadata-Version: 2.1
Name: imessageToolHp-package
Version: 0.1
Summary: imessage info
Author: hp Lin
Author-email: L_hp777@163.com
